{
  "prepare_queue": {
    "installed": [],
    "uninstalled": []
  },
  "config_munge": {
    "files": {}
  },
  "installed_plugins": {
    "cordova-plugin-camera": {
      "PACKAGE_NAME": "org.idface.com"
    },
    "cordova-plugin-camera-preview": {
      "PACKAGE_NAME": "org.idface.com"
    },
    "cordova-plugin-screen-orientation": {
      "PACKAGE_NAME": "org.idface.com"
    },
    "cordova-plugin-statusbar": {
      "PACKAGE_NAME": "org.idface.com"
    },
    "cordova-plugin-whitelist": {
      "PACKAGE_NAME": "org.idface.com"
    }
  },
  "dependent_plugins": {
    "es6-promise-plugin": {
      "PACKAGE_NAME": "org.idface.com"
    }
  }
}